adapters/CLAUDE.md
adapters/__init__.py
adapters/azure_devops/CLAUDE.md
adapters/azure_devops/README.md
adapters/azure_devops/__init__.py
adapters/azure_devops/bulk_operations.py
adapters/azure_devops/cli_wrapper.py
adapters/azure_devops/field_mapper.py
adapters/azure_devops/type_mapper.py
adapters/file_based/__init__.py
agents/CLAUDE.md
agents/README.md
agents/__init__.py
agents/registry.py
agents/templates/architect.j2
agents/templates/business-analyst.j2
agents/templates/engineer.j2
agents/templates/qa-tester.j2
agents/templates/scrum-master.j2
agents/templates/security-specialist.j2
agents/templates/senior-engineer.j2
agents/templates/slash-command.j2
agents/templates/tester.j2
agents/templates/ux-designer.j2
cli/CLAUDE.md
cli/README.md
cli/__init__.py
cli/main.py
cli/permissions_generator.py
cli/platform_detector.py
cli/commands/CLAUDE.md
cli/commands/README.md
cli/commands/__init__.py
cli/commands/agent.py
cli/commands/configure.py
cli/commands/context.py
cli/commands/doctor.py
cli/commands/init.py
cli/commands/learnings.py
cli/commands/permissions.py
cli/commands/skill.py
cli/commands/status.py
cli/commands/validate.py
cli/commands/validate_docs.py
cli/commands/workflow.py
cli/config_generators/__init__.py
cli/config_generators/jest_generator.py
cli/config_generators/pytest_generator.py
config/CLAUDE.md
config/README.md
config/__init__.py
config/loader.py
config/schema.py
config/test_taxonomy.py
core/CLAUDE.md
core/README.md
core/__init__.py
core/context_loader.py
core/directed_loader.py
core/optimized_loader.py
core/profiler.py
core/state_manager.py
skills/CLAUDE.md
skills/README.md
skills/__init__.py
skills/base.py
skills/registry.py
skills/azure_devops/CLAUDE.md
skills/azure_devops/README.md
skills/azure_devops/__init__.py
skills/azure_devops/cli_wrapper.py
skills/context/__init__.py
skills/coordination/__init__.py
skills/learnings/__init__.py
skills/work_tracking/__init__.py
skills/workflow/__init__.py
tests/CLAUDE.md
tests/README.md
tests/__init__.py
trustable_ai-2.1.0.dist-info/licenses/LICENSE
trustable_ai-2.1.0.dist-info/METADATA
trustable_ai-2.1.0.dist-info/WHEEL
trustable_ai-2.1.0.dist-info/entry_points.txt
trustable_ai-2.1.0.dist-info/top_level.txt
trustable_ai-2.1.0.dist-info/RECORD
