Metadata-Version: 2.4
Name: trustable-ai
Version: 2.1.0
Summary: AI-assisted software lifecycle tools with multi-agent orchestration, state management, and work tracking integration
Home-page: https://github.com/keychain-io/trustable-ai
Author: Trustable AI Contributors
License-Expression: MIT
Project-URL: Homepage, https://github.com/keychain-io/trustable-ai
Project-URL: Documentation, https://github.com/keychain-io/trustable-ai/blob/main/README.md
Project-URL: Repository, https://github.com/keychain-io/trustable-ai
Project-URL: Issues, https://github.com/keychain-io/trustable-ai/issues
Keywords: ai,development,workflow,automation,multi-agent,claude,devops,software-development
Classifier: Development Status :: 4 - Beta
Classifier: Intended Audience :: Developers
Classifier: Topic :: Software Development :: Libraries :: Application Frameworks
Classifier: Programming Language :: Python :: 3
Classifier: Programming Language :: Python :: 3.9
Classifier: Programming Language :: Python :: 3.10
Classifier: Programming Language :: Python :: 3.11
Classifier: Programming Language :: Python :: 3.12
Requires-Python: >=3.9
License-File: LICENSE
Requires-Dist: pyyaml>=6.0
Requires-Dist: jinja2>=3.1.0
Requires-Dist: click>=8.1.0
Requires-Dist: pydantic>=2.0.0
Requires-Dist: requests>=2.31.0
Provides-Extra: dev
Requires-Dist: pytest>=7.0.0; extra == "dev"
Requires-Dist: pytest-cov>=4.0.0; extra == "dev"
Requires-Dist: black>=23.0.0; extra == "dev"
Requires-Dist: ruff>=0.1.0; extra == "dev"
Requires-Dist: mypy>=1.0.0; extra == "dev"
Dynamic: home-page
Dynamic: license-file
Dynamic: requires-python
